MANIFEST.in
README.md
requirements.txt
setup.py
client_python_tool/__init__.py
client_python_tool/exceptions.py
client_python_tool/fvnhash.py
client_python_tool/param_encode.py
client_python_tool/testfile.py
client_python_tool.egg-info/PKG-INFO
client_python_tool.egg-info/SOURCES.txt
client_python_tool.egg-info/dependency_links.txt
client_python_tool.egg-info/not-zip-safe
client_python_tool.egg-info/requires.txt
client_python_tool.egg-info/top_level.txt
client_python_tool/packages/__init__.py
client_python_tool/packages/eth_abi/__init__.py
client_python_tool/packages/eth_abi/abi.py
client_python_tool/packages/eth_abi/base.py
client_python_tool/packages/eth_abi/constants.py
client_python_tool/packages/eth_abi/decoding.py
client_python_tool/packages/eth_abi/encoding.py
client_python_tool/packages/eth_abi/exceptions.py
client_python_tool/packages/eth_abi/grammar.py
client_python_tool/packages/eth_abi/registry.py
client_python_tool/packages/eth_abi/utils/__init__.py
client_python_tool/packages/eth_abi/utils/numeric.py
client_python_tool/packages/eth_abi/utils/padding.py
client_python_tool/packages/eth_abi/utils/parsing.py
client_python_tool/packages/eth_typing/__init__.py
client_python_tool/packages/eth_typing/abi.py
client_python_tool/packages/eth_typing/bls.py
client_python_tool/packages/eth_typing/encoding.py
client_python_tool/packages/eth_typing/enums.py
client_python_tool/packages/eth_typing/ethpm.py
client_python_tool/packages/eth_typing/evm.py
client_python_tool/packages/eth_utils/__init__.py
client_python_tool/packages/eth_utils/__main__.py
client_python_tool/packages/eth_utils/abi.py
client_python_tool/packages/eth_utils/address.py
client_python_tool/packages/eth_utils/applicators.py
client_python_tool/packages/eth_utils/conversions.py
client_python_tool/packages/eth_utils/crypto.py
client_python_tool/packages/eth_utils/currency.py
client_python_tool/packages/eth_utils/debug.py
client_python_tool/packages/eth_utils/decorators.py
client_python_tool/packages/eth_utils/encoding.py
client_python_tool/packages/eth_utils/exceptions.py
client_python_tool/packages/eth_utils/functional.py
client_python_tool/packages/eth_utils/hexadecimal.py
client_python_tool/packages/eth_utils/humanize.py
