Metadata-Version: 1.2
Name: client-python-tool
Version: 0.7.4.3
Summary: PlatON client-python-tool python tool
Home-page: https://github.com/jiuen1115/client-python-tool
Author: john zhang
Author-email: zhangjiuen@matrixelements.com
License: MIT
Keywords: platon
Platform: UNKNOWN
Classifier: Development Status :: 5 - Production/Stable
Classifier: Intended Audience :: Developers
Classifier: License :: OSI Approved :: MIT License
Classifier: Natural Language :: English
Classifier: Programming Language :: Python :: 3
Classifier: Programming Language :: Python :: 3.6
Classifier: Programming Language :: Python :: 3.7
Requires-Python: >=3.6,<4
